{
  "version": "5",
  "dialect": "mysql",
  "id": "5cad6da3-fd21-4ea9-99cd-af00df82b362",
  "prevId": "18e8addc-d747-4bfc-9306-363cae836a4c",
  "tables": {
    "categorieen": {
      "name": "categorieen",
      "columns": {
        "categorieID": {
          "name": "categorieID",
          "type": "int",
          "primaryKey": false,
          "notNull": true,
          "autoincrement": true
        },
        "categorienaam": {
          "name": "categorienaam",
          "type": "text",
          "primaryKey": false,
          "notNull": true,
          "autoincrement": false
        },
        "type": {
          "name": "type",
          "type": "enum('IN','UIT')",
          "primaryKey": false,
          "notNull": true,
          "autoincrement": false
        }
      },
      "indexes": {},
      "foreignKeys": {},
      "compositePrimaryKeys": {
        "categorieen_categorieID": {
          "name": "categorieen_categorieID",
          "columns": [
            "categorieID"
          ]
        }
      },
      "uniqueConstraints": {},
      "checkConstraint": {}
    },
    "transactieCategorie": {
      "name": "transactieCategorie",
      "columns": {
        "transactieID": {
          "name": "transactieID",
          "type": "int",
          "primaryKey": false,
          "notNull": true,
          "autoincrement": false
        },
        "categorieID": {
          "name": "categorieID",
          "type": "int",
          "primaryKey": false,
          "notNull": true,
          "autoincrement": false
        }
      },
      "indexes": {},
      "foreignKeys": {},
      "compositePrimaryKeys": {
        "transactieCategorie_transactieID_categorieID_pk": {
          "name": "transactieCategorie_transactieID_categorieID_pk",
          "columns": [
            "transactieID",
            "categorieID"
          ]
        }
      },
      "uniqueConstraints": {},
      "checkConstraint": {}
    },
    "transacties": {
      "name": "transacties",
      "columns": {
        "transactieID": {
          "name": "transactieID",
          "type": "int",
          "primaryKey": false,
          "notNull": true,
          "autoincrement": true
        },
        "rekeningID": {
          "name": "rekeningID",
          "type": "int",
          "primaryKey": false,
          "notNull": true,
          "autoincrement": false
        },
        "userID": {
          "name": "userID",
          "type": "int",
          "primaryKey": false,
          "notNull": true,
          "autoincrement": false
        },
        "beschrijving": {
          "name": "beschrijving",
          "type": "text",
          "primaryKey": false,
          "notNull": true,
          "autoincrement": false
        },
        "in_uit": {
          "name": "in_uit",
          "type": "enum('IN','UIT')",
          "primaryKey": false,
          "notNull": true,
          "autoincrement": false
        },
        "bedrag": {
          "name": "bedrag",
          "type": "decimal(10,2)",
          "primaryKey": false,
          "notNull": true,
          "autoincrement": false
        },
        "datum": {
          "name": "datum",
          "type": "text",
          "primaryKey": false,
          "notNull": true,
          "autoincrement": false
        }
      },
      "indexes": {},
      "foreignKeys": {},
      "compositePrimaryKeys": {
        "transacties_transactieID": {
          "name": "transacties_transactieID",
          "columns": [
            "transactieID"
          ]
        }
      },
      "uniqueConstraints": {},
      "checkConstraint": {}
    },
    "users": {
      "name": "users",
      "columns": {
        "id": {
          "name": "id",
          "type": "int unsigned",
          "primaryKey": false,
          "notNull": true,
          "autoincrement": true
        },
        "voornaam": {
          "name": "voornaam",
          "type": "varchar(255)",
          "primaryKey": false,
          "notNull": true,
          "autoincrement": false
        },
        "familienaam": {
          "name": "familienaam",
          "type": "varchar(255)",
          "primaryKey": false,
          "notNull": true,
          "autoincrement": false
        },
        "email": {
          "name": "email",
          "type": "varchar(255)",
          "primaryKey": false,
          "notNull": true,
          "autoincrement": false
        },
        "password_hash": {
          "name": "password_hash",
          "type": "varchar(255)",
          "primaryKey": false,
          "notNull": true,
          "autoincrement": false
        },
        "roles": {
          "name": "roles",
          "type": "json",
          "primaryKey": false,
          "notNull": true,
          "autoincrement": false
        }
      },
      "indexes": {
        "idx_user_email_unique": {
          "name": "idx_user_email_unique",
          "columns": [
            "email"
          ],
          "isUnique": true
        }
      },
      "foreignKeys": {},
      "compositePrimaryKeys": {
        "users_id": {
          "name": "users_id",
          "columns": [
            "id"
          ]
        }
      },
      "uniqueConstraints": {},
      "checkConstraint": {}
    }
  },
  "views": {},
  "_meta": {
    "schemas": {},
    "tables": {},
    "columns": {}
  },
  "internal": {
    "tables": {},
    "indexes": {}
  }
}